nd_mlp_mixer/__init__.py
nd_mlp_mixer/dense_on_axis.py
nd_mlp_mixer/layers.py
nd_mlp_mixer/mlp.py
nd_mlp_mixer/mlp_mixer.py
nd_mlp_mixer/nd_mixer.py
nd_mlp_mixer/scalar_gate.py
nd_mlp_mixer/version.py
nd_mlp_mixer-0.1.1.dist-info/LICENSE
nd_mlp_mixer-0.1.1.dist-info/METADATA
nd_mlp_mixer-0.1.1.dist-info/WHEEL
nd_mlp_mixer-0.1.1.dist-info/top_level.txt
nd_mlp_mixer-0.1.1.dist-info/RECORD
