Metadata-Version: 2.1
Name: nd-mlp-mixer
Version: 0.1.1
Summary: MLP-Mixer for TensorFlow.
Home-page: https://github.com/sradc/nd_mlp_mixer
Author: Sidney Radcliffe
Author-email: sidneyradcliffe@gmail.com
License: Apache License 2.0
Platform: UNKNOWN
Classifier: Programming Language :: Python :: 3
Classifier: Operating System :: OS Independent
Requires-Python: >=3.7
Requires-Dist: tensorflow
Requires-Dist: einops
